setup.py
ssl.py
micropython_ssl.egg-info/PKG-INFO
micropython_ssl.egg-info/SOURCES.txt
micropython_ssl.egg-info/dependency_links.txt
micropython_ssl.egg-info/top_level.txt