Metadata-Version: 1.0
Name: micropython-ssl
Version: 0.1
Summary: Dummy ssl module for MicroPython
Home-page: https://github.com/micropython/micropython-lib
Author: micropython-lib Developers
Author-email: micro-python@googlegroups.com
License: MIT
Platform: UNKNOWN
